qianfan/__init__.py
qianfan/autotuner/__init__.py
qianfan/autotuner/context.py
qianfan/autotuner/launcher.py
qianfan/autotuner/runner/__init__.py
qianfan/autotuner/runner/base.py
qianfan/autotuner/runner/infer_runner.py
qianfan/autotuner/runner/qianfan_runner.py
qianfan/autotuner/space.py
qianfan/autotuner/suggestor/__init__.py
qianfan/autotuner/suggestor/base.py
qianfan/autotuner/suggestor/random_suggestor.py
qianfan/autotuner/tune.py
qianfan/autotuner/utils.py
qianfan/client/__init__.py
qianfan/client/client.py
qianfan/common/__init__.py
qianfan/common/cli/__init__.py
qianfan/common/cli/api.py
qianfan/common/cli/chat.py
qianfan/common/cli/completion.py
qianfan/common/cli/dataset.py
qianfan/common/cli/embedding.py
qianfan/common/cli/evaluation.py
qianfan/common/cli/main.py
qianfan/common/cli/openai_adapter.py
qianfan/common/cli/plugin.py
qianfan/common/cli/proxy.py
qianfan/common/cli/trainer.py
qianfan/common/cli/txt2img.py
qianfan/common/cli/utils.py
qianfan/common/hub/__init__.py
qianfan/common/hub/hub.py
qianfan/common/hub/interface.py
qianfan/common/persister/__init__.py
qianfan/common/persister/base.py
qianfan/common/persister/persist.py
qianfan/common/prompt/__init__.py
qianfan/common/prompt/prompt.py
qianfan/common/prompt/template.py
qianfan/common/runnable/__init__.py
qianfan/common/runnable/base.py
qianfan/common/tool/baidu_search_tool.py
qianfan/common/tool/base_tool.py
qianfan/common/tool/duckduckgo_search_tool.py
qianfan/common/tool/wikipedia_tool.py
qianfan/config.py
qianfan/consts.py
qianfan/dataset/__init__.py
qianfan/dataset/consts.py
qianfan/dataset/data_insight/__init__.py
qianfan/dataset/data_insight/assets/index.html
qianfan/dataset/data_insight/data_insight_utils.py
qianfan/dataset/data_insight/insight.py
qianfan/dataset/data_operator.py
qianfan/dataset/data_source/__init__.py
qianfan/dataset/data_source/afs.py
qianfan/dataset/data_source/baidu_qianfan.py
qianfan/dataset/data_source/base.py
qianfan/dataset/data_source/bos.py
qianfan-0.4.12.2.dist-info/METADATA
qianfan-0.4.12.2.dist-info/WHEEL
qianfan-0.4.12.2.dist-info/entry_points.txt
qianfan-0.4.12.2.dist-info/RECORD
