Metadata-Version: 2.1
Name: qianfan
Version: 0.4.12.2
Summary: 文心千帆大模型平台 Python SDK
Home-page: https://cloud.baidu.com/product/wenxinworkshop
License: Apache-2.0
Keywords: baidu,qianfan
Requires-Python: >=3.7,<4
Classifier: License :: OSI Approved :: Apache Software License
Classifier: Programming Language :: Python :: 3
Classifier: Programming Language :: Python :: 3.7
Classifier: Programming Language :: Python :: 3.8
Classifier: Programming Language :: Python :: 3.9
Classifier: Programming Language :: Python :: 3.10
Classifier: Programming Language :: Python :: 3.11
Classifier: Programming Language :: Python :: 3.12
Classifier: Programming Language :: Python :: 3.13
Provides-Extra: all
Provides-Extra: dataset-base
Provides-Extra: langchain
Provides-Extra: local-data-clean
Provides-Extra: openai
Requires-Dist: aiohttp (>=3.7.0)
Requires-Dist: aiolimiter (>=1.1.0)
Requires-Dist: bce-python-sdk (>=0.8.79)
Requires-Dist: cachetools (>=5.0.0)
Requires-Dist: diskcache (>=5.6.3)
Requires-Dist: emoji (>=2.2.0) ; extra == "local-data-clean" or extra == "all"
Requires-Dist: fastapi (>=0.85.0) ; extra == "openai" or extra == "all"
Requires-Dist: filelock (>=3.7.0) ; extra == "dataset-base" or extra == "local-data-clean" or extra == "all"
Requires-Dist: ijson (>=3.0) ; extra == "dataset-base" or extra == "local-data-clean" or extra == "all"
Requires-Dist: importlib-metadata (>=1.4.0) ; python_full_version <= "3.7.0"
Requires-Dist: langchain (>=0.1.10) ; (python_full_version >= "3.8.1") and (extra == "langchain" or extra == "all")
Requires-Dist: langchain-community (>=0.2.0) ; (python_full_version >= "3.8.1") and (extra == "langchain" or extra == "all")
Requires-Dist: locust (>=2.9.0) ; extra == "dataset-base" or extra == "local-data-clean" or extra == "all"
Requires-Dist: ltp (>=4.2.0) ; extra == "local-data-clean" or extra == "all"
Requires-Dist: multiprocess (>=0.70.12)
Requires-Dist: numpy (<1.22.0) ; (python_version >= "3.7" and python_version < "3.8") and (extra == "dataset-base" or extra == "local-data-clean" or extra == "all")
Requires-Dist: numpy (>=1.22.0) ; (python_version >= "3.8") and (extra == "dataset-base" or extra == "local-data-clean" or extra == "all")
Requires-Dist: prompt-toolkit (>=3.0.38)
Requires-Dist: pyarrow (<=12.0.1) ; (python_version >= "3.7" and python_version < "3.8") and (extra == "dataset-base" or extra == "local-data-clean" or extra == "all")
Requires-Dist: pyarrow (>=14.0.1) ; (python_version >= "3.8") and (extra == "dataset-base" or extra == "local-data-clean" or extra == "all")
Requires-Dist: pydantic (>=1.0)
Requires-Dist: python-dateutil (>=2.8.2,<3.0.0) ; extra == "dataset-base" or extra == "local-data-clean" or extra == "all"
Requires-Dist: python-dotenv (<=0.21.1) ; python_version < "3.8"
Requires-Dist: python-dotenv (>=1.0) ; python_version >= "3.8"
Requires-Dist: pyyaml (>=6.0.1,<7.0.0)
Requires-Dist: requests (>=2.24)
Requires-Dist: rich (>=13.0.0)
Requires-Dist: sentencepiece (>=0.1.98) ; extra == "local-data-clean" or extra == "all"
Requires-Dist: tabulate (>=0.9.0) ; extra == "dataset-base" or extra == "local-data-clean" or extra == "all"
Requires-Dist: tenacity (>=8.2.3,<9.0.0)
Requires-Dist: torch (<=1.13.1) ; (python_version < "3.8") and (extra == "local-data-clean" or extra == "all")
Requires-Dist: torch (>=1.4.0) ; (python_version >= "3.8") and (extra == "local-data-clean" or extra == "all")
Requires-Dist: typer (>=0.9.0)
Requires-Dist: typing-extensions (>=4.0.0) ; python_full_version <= "3.10.0"
Requires-Dist: uvicorn (>=0.15.0) ; extra == "openai" or extra == "all"
Project-URL: Documentation, https://qianfan.readthedocs.io/en/stable/README.html
Project-URL: Repository, https://github.com/baidubce/bce-qianfan-sdk
